pyspiro/__init__.py
pyspiro/data/__init__.py
pyspiro/data/bowermann_2022_coefficients.csv
pyspiro/data/bowermann_2022_splines.csv
pyspiro/data/gli_2012_coefficients.csv
pyspiro/data/gli_2012_splines.csv
pyspiro/data/gli_2017_coefficients.csv
pyspiro/data/gli_2017_splines.csv
pyspiro/data/gli_2021_coefficients.csv
pyspiro/data/gli_2021_splines.csv
pyspiro/data/pyspiro_250x.png
pyspiro/data/scapis_2023_coefficients.csv
pyspiro/data/scapis_2023_splines.csv
pyspiro/data/schulz_2013_splines.csv
pyspiro/data/test_file.csv
pyspiro/src/BOWERMANN_2022.py
pyspiro/src/GLI_2012.py
pyspiro/src/GLI_2017.py
pyspiro/src/GLI_2021.py
pyspiro/src/KUSTER_2008.py
pyspiro/src/SCAPIS_2023.py
pyspiro/src/SCHULZ_2013.py
pyspiro/src/__init__.py
pyspiro/src/reference.py
pyspiro-0.3.6.dist-info/licenses/LICENSE
pyspiro-0.3.6.dist-info/METADATA
pyspiro-0.3.6.dist-info/WHEEL
pyspiro-0.3.6.dist-info/top_level.txt
pyspiro-0.3.6.dist-info/RECORD
